yaal/__init__.py
yaal/cli.py
yaal/grammar.lark
yaal/parser.py
yaal-0.1.0.dist-info/METADATA
yaal-0.1.0.dist-info/WHEEL
yaal-0.1.0.dist-info/entry_points.txt
yaal-0.1.0.dist-info/RECORD
