Metadata-Version: 2.4
Name: yaal
Version: 0.1.0
Summary: YAAL (Yet Another Abstract Language) Parser - A human-readable configuration language with executable code blocks
Project-URL: Homepage, https://github.com/example/yaal
Project-URL: Repository, https://github.com/example/yaal
Project-URL: Documentation, https://yaal.readthedocs.io
Project-URL: Bug Tracker, https://github.com/example/yaal/issues
Author-email: YAAL Development Team <dev@yaal.example.com>
Keywords: configuration,dsl,language,parser,yaal
Classifier: Development Status :: 4 - Beta
Classifier: Intended Audience :: Developers
Classifier: License :: OSI Approved :: MIT License
Classifier: Programming Language :: Python :: 3
Classifier: Programming Language :: Python :: 3.8
Classifier: Programming Language :: Python :: 3.9
Classifier: Programming Language :: Python :: 3.10
Classifier: Programming Language :: Python :: 3.11
Classifier: Programming Language :: Python :: 3.12
Classifier: Topic :: Software Development :: Libraries :: Python Modules
Classifier: Topic :: Text Processing :: Markup
Requires-Python: >=3.8.1
Requires-Dist: lark>=1.1.0
Provides-Extra: dev
Requires-Dist: black>=23.0.0; extra == 'dev'
Requires-Dist: flake8>=6.0.0; extra == 'dev'
Requires-Dist: isort>=5.12.0; extra == 'dev'
Requires-Dist: mypy>=1.0.0; extra == 'dev'
Requires-Dist: pytest-cov>=4.0.0; extra == 'dev'
Requires-Dist: pytest>=7.0.0; extra == 'dev'
Provides-Extra: docs
Requires-Dist: myst-parser>=1.0.0; extra == 'docs'
Requires-Dist: sphinx-rtd-theme>=1.2.0; extra == 'docs'
Requires-Dist: sphinx>=5.0.0; extra == 'docs'
Provides-Extra: testing
Requires-Dist: pytest-cov>=4.0.0; extra == 'testing'
Requires-Dist: pytest>=7.0.0; extra == 'testing'
